cinol/__init__.py
cinol/encryptor.py
cinol/license.py
cinol/obfuscator.py
cinol/runtime.py
cinol/utils/__init__.py
cinol/utils/anti_tampering.py
cinol/utils/keygen.py
cinol-0.1.0.dist-info/METADATA
cinol-0.1.0.dist-info/WHEEL
cinol-0.1.0.dist-info/top_level.txt
cinol-0.1.0.dist-info/RECORD
