Metadata-Version: 2.4
Name: cinol
Version: 0.1.0
Summary: Python Code Protection Toolkit (Obfuscation + Encryption + License)
Home-page: https://github.com/Eternals-Satya/cinol
Author: Cansila
Author-email: Cans Vlazars <eternals.tolong@gmail.com>
License: MIT
Project-URL: Homepage, https://github.com/Eternals-Satya/cinol
Keywords: obfuscation,encryption,license,protection
Classifier: Programming Language :: Python :: 3
Classifier: License :: OSI Approved :: MIT License
Classifier: Topic :: Software Development :: Libraries
Requires-Dist: pycryptodome>=3.15.0
Requires-Dist: astunparse>=1.6.3
Provides-Extra: dev
Requires-Dist: pytest; extra == "dev"
Requires-Dist: cython; extra == "dev"
Dynamic: author
Dynamic: home-page
